houseparty/__init__.py
houseparty/houseparty.py
houseparty-1.0.1.dist-info/LICENSE
houseparty-1.0.1.dist-info/METADATA
houseparty-1.0.1.dist-info/WHEEL
houseparty-1.0.1.dist-info/top_level.txt
houseparty-1.0.1.dist-info/RECORD
