Metadata-Version: 2.1
Name: houseparty
Version: 1.0.1
Summary: Python package to interact with Houseparty's API.
Home-page: https://github.com/milesrack/houseparty
Author: Miles Rack
Author-email: milesr4@protonmail.com
License: MIT
Keywords: python,houseparty,api,houseparty-app
Platform: UNKNOWN
Classifier: Intended Audience :: Developers
Classifier: Programming Language :: Python
Classifier: Programming Language :: Python :: 3.9
Requires-Dist: requests
